README.md
setup.py
globomap_monitoring/__init__.py
globomap_monitoring/settings.py
globomap_monitoring/zbx_passive.py
globomap_monitoring.egg-info/PKG-INFO
globomap_monitoring.egg-info/SOURCES.txt
globomap_monitoring.egg-info/dependency_links.txt
globomap_monitoring.egg-info/requires.txt
globomap_monitoring.egg-info/top_level.txt