Metadata-Version: 1.0
Name: globomap-monitoring
Version: 0.0.1
Summary: Lib to centralizer monitoring of GloboMap
Home-page: https://github.com/globocom/globomap-monitoring
Author: Ederson Brilhante
Author-email: ederson.brilhante@corp.globo.com
License: UNKNOWN
Platform: UNKNOWN
